{
  "StatusCode": 0,
  "HostAddr": "000.00.000.00",
  "Result": {
    "to_station": {
      "id": 10,
      "fare_calculator_id": 7,
      "address": "O.R. Tambo Int. Airport",
      "name": "O.R. Tambo Int. Airport Station",
      "longitude": 28.232055,
      "latitude": -26.133492,
      "short_name": "O.R. Tambo"
    },
    "day_type": {
      "id": 0,
      "name": "Saturdays and Public Holidays"
    },
    "transfer": true,
    "instructions": "From Pretoria Station to O.R. Tambo Int. Airport Station: Take the North-South line. Transfer at Marlboro Station to the West-East line. Use only FRONT two coaches.",
    "from_route": {
      "id": 1,
      "description": "North - South Commuter link",
      "name": "Hatfield to Park",
      "short_name": "North-South"
    },
    "from_station": {
      "id": 2,
      "fare_calculator_id": 2,
      "address": "Andries Street and Paul Kruger Street",
      "name": "Pretoria Station",
      "longitude": 28.190963,
      "latitude": -25.760197,
      "short_name": "Pretoria"
    },
    "entries": [
      {
        "transferDepartTime": "06:01",
        "transferArriveTime": "05:55",
        "toCars": 4,
        "fromCars": 4,
        "fromTime": "05:33",
        "toTime": "06:11"
      },
      {
        "transferDepartTime": "06:31",
        "transferArriveTime": "06:25",
        "toCars": 4,
        "fromCars": 4,
        "fromTime": "06:03",
        "toTime": "06:41"
      },
      {
        "transferDepartTime": "07:01",
        "transferArriveTime": "06:55",
        "toCars": 4,
        "fromCars": 4,
        "fromTime": "06:33",
        "toTime": "07:11"
      },
      {
        "transferDepartTime": "07:31",
        "transferArriveTime": "07:25",
        "toCars": 4,
        "fromCars": 4,
        "fromTime": "07:03",
        "toTime": "07:41"
      },
      {
        "transferDepartTime": "08:01",
        "transferArriveTime": "07:55",
        "toCars": 4,
        "fromCars": 4,
        "fromTime": "07:33",
        "toTime": "08:11"
      },
      {
        "transferDepartTime": "08:31",
        "transferArriveTime": "08:25",
        "toCars": 4,
        "fromCars": 4,
        "fromTime": "08:03",
        "toTime": "08:41"
      },
      {
        "transferDepartTime": "09:01",
        "transferArriveTime": "08:55",
        "toCars": 4,
        "fromCars": 4,
        "fromTime": "08:33",
        "toTime": "09:11"
      },
      {
        "transferDepartTime": "09:31",
        "transferArriveTime": "09:25",
        "toCars": 4,
        "fromCars": 4,
        "fromTime": "09:03",
        "toTime": "09:41"
      },
      {
        "transferDepartTime": "10:01",
        "transferArriveTime": "09:55",
        "toCars": 4,
        "fromCars": 4,
        "fromTime": "09:33",
        "toTime": "10:11"
      },
      {
        "transferDepartTime": "10:31",
        "transferArriveTime": "10:25",
        "toCars": 4,
        "fromCars": 4,
        "fromTime": "10:03",
        "toTime": "10:41"
      },
      {
        "transferDepartTime": "11:01",
        "transferArriveTime": "10:55",
        "toCars": 4,
        "fromCars": 4,
        "fromTime": "10:33",
        "toTime": "11:11"
      },
      {
        "transferDepartTime": "11:31",
        "transferArriveTime": "11:25",
        "toCars": 4,
        "fromCars": 4,
        "fromTime": "11:03",
        "toTime": "11:41"
      },
      {
        "transferDepartTime": "12:01",
        "transferArriveTime": "11:55",
        "toCars": 4,
        "fromCars": 4,
        "fromTime": "11:33",
        "toTime": "12:11"
      },
      {
        "transferDepartTime": "12:31",
        "transferArriveTime": "12:25",
        "toCars": 4,
        "fromCars": 4,
        "fromTime": "12:03",
        "toTime": "12:41"
      },
      {
        "transferDepartTime": "13:01",
        "transferArriveTime": "12:55",
        "toCars": 4,
        "fromCars": 4,
        "fromTime": "12:33",
        "toTime": "13:11"
      },
      {
        "transferDepartTime": "13:31",
        "transferArriveTime": "13:25",
        "toCars": 4,
        "fromCars": 4,
        "fromTime": "13:03",
        "toTime": "13:41"
      },
      {
        "transferDepartTime": "14:01",
        "transferArriveTime": "13:55",
        "toCars": 4,
        "fromCars": 4,
        "fromTime": "13:33",
        "toTime": "14:11"
      },
      {
        "transferDepartTime": "14:31",
        "transferArriveTime": "14:25",
        "toCars": 4,
        "fromCars": 4,
        "fromTime": "14:03",
        "toTime": "14:41"
      },
      {
        "transferDepartTime": "15:01",
        "transferArriveTime": "14:55",
        "toCars": 4,
        "fromCars": 4,
        "fromTime": "14:33",
        "toTime": "15:11"
      },
      {
        "transferDepartTime": "15:31",
        "transferArriveTime": "15:25",
        "toCars": 4,
        "fromCars": 4,
        "fromTime": "15:03",
        "toTime": "15:41"
      },
      {
        "transferDepartTime": "16:01",
        "transferArriveTime": "15:55",
        "toCars": 4,
        "fromCars": 4,
        "fromTime": "15:33",
        "toTime": "16:11"
      },
      {
        "transferDepartTime": "16:31",
        "transferArriveTime": "16:25",
        "toCars": 4,
        "fromCars": 4,
        "fromTime": "16:03",
        "toTime": "16:41"
      },
      {
        "transferDepartTime": "17:01",
        "transferArriveTime": "16:55",
        "toCars": 4,
        "fromCars": 4,
        "fromTime": "16:33",
        "toTime": "17:11"
      },
      {
        "transferDepartTime": "17:31",
        "transferArriveTime": "17:25",
        "toCars": 4,
        "fromCars": 4,
        "fromTime": "17:03",
        "toTime": "17:41"
      },
      {
        "transferDepartTime": "18:01",
        "transferArriveTime": "17:55",
        "toCars": 4,
        "fromCars": 4,
        "fromTime": "17:33",
        "toTime": "18:11"
      },
      {
        "transferDepartTime": "18:31",
        "transferArriveTime": "18:25",
        "toCars": 4,
        "fromCars": 4,
        "fromTime": "18:03",
        "toTime": "18:41"
      },
      {
        "transferDepartTime": "19:01",
        "transferArriveTime": "18:55",
        "toCars": 4,
        "fromCars": 4,
        "fromTime": "18:33",
        "toTime": "19:11"
      },
      {
        "transferDepartTime": "19:31",
        "transferArriveTime": "19:25",
        "toCars": 4,
        "fromCars": 4,
        "fromTime": "19:03",
        "toTime": "19:41"
      },
      {
        "transferDepartTime": "20:01",
        "transferArriveTime": "19:55",
        "toCars": 4,
        "fromCars": 4,
        "fromTime": "19:33",
        "toTime": "20:11"
      },
      {
        "transferDepartTime": "20:32",
        "transferArriveTime": "20:25",
        "toCars": 4,
        "fromCars": 4,
        "fromTime": "20:03",
        "toTime": "20:42"
      }
    ],
    "transfer_station": {
      "id": 5,
      "fare_calculator_id": 5,
      "address": "Marlboro Drive",
      "name": "Marlboro Station",
      "longitude": 28.111108,
      "latitude": -26.083504,
      "short_name": "Marlboro"
    },
    "to_route": {
      "id": 4,
      "description": "West - East Commuter link",
      "name": "Sandton to O.R Tambo",
      "short_name": "West-East"
    }
  },
  "Host": "000.0.0.0",
  "ResponseTime": 1006,
  "Timestamp": "Tue May 28 11:17:00 SAST 2013",
  "HostName": "brandfusion.afrigisforms.co.za"
}